odoo/addons/l10n_es_vat_book/README.rst
odoo/addons/l10n_es_vat_book/__init__.py
odoo/addons/l10n_es_vat_book/__manifest__.py
odoo/addons/l10n_es_vat_book/data/aeat.vat.book.map.line.csv
odoo/addons/l10n_es_vat_book/data/l10n.es.aeat.map.tax.line.account.csv
odoo/addons/l10n_es_vat_book/data/l10n.es.aeat.map.tax.line.tax.csv
odoo/addons/l10n_es_vat_book/i18n/bg.po
odoo/addons/l10n_es_vat_book/i18n/ca.po
odoo/addons/l10n_es_vat_book/i18n/cs.po
odoo/addons/l10n_es_vat_book/i18n/de.po
odoo/addons/l10n_es_vat_book/i18n/es.po
odoo/addons/l10n_es_vat_book/i18n/es_CO.po
odoo/addons/l10n_es_vat_book/i18n/es_CR.po
odoo/addons/l10n_es_vat_book/i18n/eu.po
odoo/addons/l10n_es_vat_book/i18n/fr.po
odoo/addons/l10n_es_vat_book/i18n/gl.po
odoo/addons/l10n_es_vat_book/i18n/hr.po
odoo/addons/l10n_es_vat_book/i18n/l10n_es_vat_book.pot
odoo/addons/l10n_es_vat_book/i18n/nl.po
odoo/addons/l10n_es_vat_book/i18n/pl.po
odoo/addons/l10n_es_vat_book/i18n/pt.po
odoo/addons/l10n_es_vat_book/i18n/pt_BR.po
odoo/addons/l10n_es_vat_book/i18n/ru.po
odoo/addons/l10n_es_vat_book/i18n/sl.po
odoo/addons/l10n_es_vat_book/i18n/sv.po
odoo/addons/l10n_es_vat_book/i18n/tr.po
odoo/addons/l10n_es_vat_book/i18n/vi.po
odoo/addons/l10n_es_vat_book/migrations/18.0.2.0.0/post-migration.py
odoo/addons/l10n_es_vat_book/models/__init__.py
odoo/addons/l10n_es_vat_book/models/aeat_vat_book_map_line.py
odoo/addons/l10n_es_vat_book/models/l10n_es_vat_book.py
odoo/addons/l10n_es_vat_book/models/l10n_es_vat_book_line.py
odoo/addons/l10n_es_vat_book/models/l10n_es_vat_book_line_tax.py
odoo/addons/l10n_es_vat_book/models/l10n_es_vat_book_summary.py
odoo/addons/l10n_es_vat_book/models/l10n_es_vat_book_tax_summary.py
odoo/addons/l10n_es_vat_book/readme/CONFIGURE.md
odoo/addons/l10n_es_vat_book/readme/CONTRIBUTORS.md
odoo/addons/l10n_es_vat_book/readme/DESCRIPTION.md
odoo/addons/l10n_es_vat_book/readme/INSTALL.md
odoo/addons/l10n_es_vat_book/readme/ROADMAP.md
odoo/addons/l10n_es_vat_book/readme/USAGE.md
odoo_addon_l10n_es_vat_book-18.0.2.1.0.1.dist-info/METADATA
odoo_addon_l10n_es_vat_book-18.0.2.1.0.1.dist-info/WHEEL
odoo_addon_l10n_es_vat_book-18.0.2.1.0.1.dist-info/top_level.txt
odoo_addon_l10n_es_vat_book-18.0.2.1.0.1.dist-info/RECORD
