Metadata-Version: 2.1
Name: odoo-addon-l10n_es_vat_book
Version: 18.0.2.1.0.1
Requires-Python: >=3.10
Requires-Dist: odoo-addon-l10n_es_aeat==18.0.*
Requires-Dist: odoo-addon-report_xlsx==18.0.*
Requires-Dist: odoo==18.0.*
Summary: Libros registro del IVA y del IRPF
Home-page: https://github.com/OCA/l10n-spain
License: AGPL-3
Author: PRAXYA, ForgeFlow, Tecnativa, Odoo Community Association (OCA)
Author-email: support@odoo-community.org
Classifier: Programming Language :: Python
Classifier: Framework :: Odoo
Classifier: Framework :: Odoo :: 18.0
Classifier: License :: OSI Approved :: GNU Affero General Public License v3
